MANIFEST.in
setup.py
docs/CONTRIBUTORS.txt
docs/HISTORY.txt
docs/README.txt
docs/classes.iuml
docs/classes.png
src/ztfy/__init__.py
src/ztfy.thesaurus.egg-info/PKG-INFO
src/ztfy.thesaurus.egg-info/SOURCES.txt
src/ztfy.thesaurus.egg-info/dependency_links.txt
src/ztfy.thesaurus.egg-info/entry_points.txt
src/ztfy.thesaurus.egg-info/namespace_packages.txt
src/ztfy.thesaurus.egg-info/not-zip-safe
src/ztfy.thesaurus.egg-info/requires.txt
src/ztfy.thesaurus.egg-info/top_level.txt
src/ztfy/thesaurus/__init__.py
src/ztfy/thesaurus/configure.zcml
src/ztfy/thesaurus/database.py
src/ztfy/thesaurus/index.py
src/ztfy/thesaurus/schema.py
src/ztfy/thesaurus/security.py
src/ztfy/thesaurus/security.zcml
src/ztfy/thesaurus/term.py
src/ztfy/thesaurus/thesaurus.py
src/ztfy/thesaurus/vocabulary.py
src/ztfy/thesaurus/browser/__init__.py
src/ztfy/thesaurus/browser/configure.zcml
src/ztfy/thesaurus/browser/term.py
src/ztfy/thesaurus/browser/thesaurus.py
src/ztfy/thesaurus/browser/traverser.py
src/ztfy/thesaurus/browser/tree.py
src/ztfy/thesaurus/browser/interfaces/__init__.py
src/ztfy/thesaurus/browser/interfaces/term.py
src/ztfy/thesaurus/browser/interfaces/thesaurus.py
src/ztfy/thesaurus/browser/json/__init__.py
src/ztfy/thesaurus/browser/json/configure.zcml
src/ztfy/thesaurus/browser/json/search.py
src/ztfy/thesaurus/browser/resources/css/ztfy.thesaurus.css
src/ztfy/thesaurus/browser/resources/img/gps.png
src/ztfy/thesaurus/browser/resources/img/hidden.gif
src/ztfy/thesaurus/browser/resources/img/lline.png
src/ztfy/thesaurus/browser/resources/img/loader.gif
src/ztfy/thesaurus/browser/resources/img/locked.gif
src/ztfy/thesaurus/browser/resources/img/loupe.gif
src/ztfy/thesaurus/browser/resources/img/minus.png
src/ztfy/thesaurus/browser/resources/img/plus.png
src/ztfy/thesaurus/browser/resources/img/tline.png
src/ztfy/thesaurus/browser/resources/img/visible.gif
src/ztfy/thesaurus/browser/resources/img/vline.png
src/ztfy/thesaurus/browser/resources/js/ztfy.thesaurus.js
src/ztfy/thesaurus/browser/resources/js/ztfy.thesaurus.min.js
src/ztfy/thesaurus/browser/resources/js/i18n/fr.js
src/ztfy/thesaurus/browser/templates/extract_tree.pt
src/ztfy/thesaurus/browser/templates/terms_selector.pt
src/ztfy/thesaurus/browser/templates/terms_selector_term.pt
src/ztfy/thesaurus/browser/templates/terms_tree.pt
