Metadata-Version: 1.1
Name: ztfy.thesaurus
Version: 0.2.16.1
Summary: ZTFY thesaurus management package
Home-page: http://www.ztfy.org
Author: Thierry Florac
Author-email: tflorac@ulthar.net
License: ZPL
Platform: UNKNOWN
Classifier: Programming Language :: Python
